{
  "shift_id": 0,
  "shift_name": "",
  "start_datetime": "",
  "end_datetime": "",
  "shift_status": "",
  "department": {
    "department_id": 0,
    "department_name": ""
  },
  "work_location": {
    "work_location_id": 0,
    "location_name": ""
  },
  "required_job_roles": [
    {
      "required_employees": 0,
      "job_roles": [
        {
          "job_role_id": 0,
          "role_name": ""
        }
      ]
    }
  ],
  "shift_assignments": [
    {
      "assigned_employee": {
        "employee_id": 0,
        "first_name": "",
        "last_name": ""
      },
      "assignment_status": "",
      "assignment_date": "",
      "check_in_date": "",
      "check_out_datetime": "",
      "shift_approvals": [
        {
          "approver_employee": {
            "employee_id": 0,
            "first_name": "",
            "last_name": ""
          },
          "decision": "",
          "approval_comment": "",
          "decision_datetime": ""
        }
      ],
      "swap_requests": [
        {
          "employee_from": {
            "employee_id": 0,
            "first_name": "",
            "last_name": ""
          },
          "employee_to": {
            "employee_id": 0,
            "first_name": "",
            "last_name": ""
          },
          "swap_status": "",
          "request_datetime": "",
          "reason": "",
          "swap_approvals": [
            {
              "approver_employee": {
                "employee_id": 0,
                "first_name": "",
                "last_name": ""
              },
              "decision": "",
              "swap_comment": "",
              "decision_datetime": ""
            }
          ]
        }
      ]
    }
  ]
}